kohi/__init__.py
kohi/core.py
kohi/main.py
kohi/send.py
kohi/integrations/__init__.py
kohi/integrations/fastapi.py
kohi/integrations/flask.py
kohi_python-0.1.2.dist-info/licenses/LICENSE
kohi_python-0.1.2.dist-info/METADATA
kohi_python-0.1.2.dist-info/WHEEL
kohi_python-0.1.2.dist-info/top_level.txt
kohi_python-0.1.2.dist-info/RECORD
